kg_utils/constants.py
kg_utils/merging.py
kg_utils/utils.py
kg_utils-0.0.6.dist-info/LICENSE
kg_utils-0.0.6.dist-info/METADATA
kg_utils-0.0.6.dist-info/WHEEL
kg_utils-0.0.6.dist-info/top_level.txt
kg_utils-0.0.6.dist-info/RECORD
