Metadata-Version: 2.1
Name: kg-utils
Version: 0.0.6
Summary: Merge KGX json objects
Home-page: https://github.com/helxplatform/kg_utils
Author: Evan Morris
Author-email: 
License: MIT
Platform: UNKNOWN
Requires-Python: >=3.6
License-File: LICENSE
Requires-Dist: orjson ==3.8.10
Requires-Dist: xxhash ==3.2.0
Requires-Dist: jsonlines ==3.1.0
